magg/__init__.py
magg/__main__.py
magg/auth.py
magg/cli.py
magg/client.py
magg/kit.py
magg/messaging.py
magg/process.py
magg/reload.py
magg/settings.py
magg/discovery/__init__.py
magg/discovery/catalog.py
magg/discovery/metadata.py
magg/discovery/search.py
magg/logs/__init__.py
magg/logs/adapter.py
magg/logs/config.py
magg/logs/defaults.py
magg/logs/filter.py
magg/logs/formatter.py
magg/logs/handler.py
magg/logs/listener.py
magg/logs/queue.py
magg/mbro/__init__.py
magg/mbro/__main__.py
magg/mbro/arepl.py
magg/mbro/cli.py
magg/mbro/client.py
magg/mbro/completers.py
magg/mbro/formatter.py
magg/mbro/multiline.py
magg/mbro/parser.py
magg/proxy/__init__.py
magg/proxy/client.py
magg/proxy/mixin.py
magg/proxy/server.py
magg/proxy/types.py
magg/server/__init__.py
magg/server/__main__.py
magg/server/cli.py
magg/server/defaults.py
magg/server/manager.py
magg/server/response.py
magg/server/runner.py
magg/server/server.py
magg/test/__init__.py
magg/test/test_auth.py
magg/test/test_basic.py
magg/test/test_client_api.py
magg/test/test_client_mounting.py
magg/test/test_config.py
magg/test/test_config_migration.py
magg/test/test_config_reload.py
magg/test/test_e2e_mounting.py
magg/test/test_e2e_simple.py
magg/test/test_error_handling.py
magg/test/test_in_memory.py
magg/test/test_integration.py
magg/test/test_kit.py
magg/test/test_kit_tools.py
magg/test/test_messaging.py
magg/test/test_messaging_integration.py
magg/test/test_mounting.py
magg/test/test_mounting_debug.py
magg/test/test_mounting_real.py
magg/test/test_server_add.py
magg/test/test_server_removal.py
magg/test/test_status_check.py
magg/test/test_tool_delegation.py
magg/test/test_transport.py
magg/test/mbro/__init__.py
magg/test/mbro/test_basic_functionality.py
magg/test/mbro/test_cli.py
magg/test/mbro/test_client.py
magg/test/mbro/test_integration.py
magg/test/mbro/test_json_parsing.py
magg/test/mbro/test_search_functionality.py
magg/test/mbro/test_tool_calling.py
magg/util/__init__.py
magg/util/system.py
mseep_magg-0.7.1.dist-info/METADATA
mseep_magg-0.7.1.dist-info/WHEEL
mseep_magg-0.7.1.dist-info/top_level.txt
mseep_magg-0.7.1.dist-info/RECORD
