Metadata-Version: 2.4
Name: mseep-magg
Version: 0.7.1
Summary: MCP Aggregator
Home-page: https://github.com/mseep
Author: mseep
Author-email: support@skydeck.ai
Maintainer: mseep
Maintainer-email: support@skydeck.ai
Keywords: mseep,model,context,protocol,ai,agent,mcp,aggregator,proxy,fastmcp,aiohttp,pydantic,pydantic-settings,rich
Classifier: Programming Language :: Python :: 3
Classifier: License :: OSI Approved :: MIT License
Classifier: Operating System :: OS Independent
Requires-Python: >=3.6
Requires-Dist: fastmcp>=2.8.0
Requires-Dist: aiohttp>=3.12.13
Requires-Dist: pydantic>=2.11.7
Requires-Dist: pydantic-settings>=2.10.0
Requires-Dist: rich>=14.0.0
Requires-Dist: prompt-toolkit>=3.0.51
Requires-Dist: cryptography>=45.0.4
Requires-Dist: pyjwt>=2.10.1
Requires-Dist: watchdog>=6.0.0
Requires-Dist: art>=6.5
Dynamic: author
Dynamic: author-email
Dynamic: classifier
Dynamic: description
Dynamic: description-content-type
Dynamic: home-page
Dynamic: keywords
Dynamic: maintainer
Dynamic: maintainer-email
Dynamic: requires-dist
Dynamic: requires-python
Dynamic: summary
